twotwo/__init__.py
twotwo/main.py
twotwo-0.0.1.dist-info/LICENSE
twotwo-0.0.1.dist-info/METADATA
twotwo-0.0.1.dist-info/WHEEL
twotwo-0.0.1.dist-info/top_level.txt
twotwo-0.0.1.dist-info/RECORD
