Metadata-Version: 2.1
Name: twotwo
Version: 0.0.1
Summary: Solve 2x2 rubik's cube
Home-page: https://github.com/MDAddario/twotwo
Author: Michael Lindner-D'Addario
Author-email: michael.lindner.daddario@gmail.com
License: UNKNOWN
Platform: UNKNOWN
Classifier: Programming Language :: Python :: 3
Classifier: License :: OSI Approved :: MIT License
Classifier: Operating System :: OS Independent
Requires-Python: >=3.6
License-File: LICENSE
